mscoppelpvm/Base.py
mscoppelpvm/ErrorMs.py
mscoppelpvm/Fork.py
mscoppelpvm/ForkHttp.py
mscoppelpvm/HttpErrors.py
mscoppelpvm/HttpResponse.py
mscoppelpvm/HttpTransit.py
mscoppelpvm/LogssBottle.py
mscoppelpvm/MsManager.py
mscoppelpvm/NatsBase.py
mscoppelpvm/Util.py
mscoppelpvm/Worker.py
mscoppelpvm/__init__.py
mscoppelpvm/http_server.py
mscoppelpvm/loggs.py
mscoppelpvm/loggsWrapper.py
mscoppelpvm/microservices.py
mscoppelpvm/ms_base.py
mscoppelpvm/options.py
mscoppelpvm/types.py
mscoppelpvm/version_framework.py
MsCoppelPVM-2.0.3.dist-info/METADATA
MsCoppelPVM-2.0.3.dist-info/WHEEL
MsCoppelPVM-2.0.3.dist-info/top_level.txt
MsCoppelPVM-2.0.3.dist-info/RECORD
