Metadata-Version: 2.1
Name: MsCoppelPVM
Version: 2.0.3
Summary: UNKNOWN
Home-page: UNKNOWN
Author: Ulises Cabrera
Author-email: ulises.cabrera@coppel.com
License: MIT
Platform: UNKNOWN
Classifier: Programming Language :: Python :: 3
Classifier: License :: OSI Approved :: MIT License
Classifier: Operating System :: OS Independent
